LICENSE.txt
MANIFEST.in
NOTICE.txt
README.md
setup.cfg
setup.py
amazon_kclpy/__init__.py
amazon_kclpy/kcl.py
amazon_kclpy/jars/__init__.py
amazon_kclpy/jars/amazon-kinesis-client-1.6.4.jar
amazon_kclpy/jars/aws-java-sdk-cloudwatch-1.11.14.jar
amazon_kclpy/jars/aws-java-sdk-core-1.11.14.jar
amazon_kclpy/jars/aws-java-sdk-dynamodb-1.11.14.jar
amazon_kclpy/jars/aws-java-sdk-kinesis-1.11.14.jar
amazon_kclpy/jars/aws-java-sdk-kms-1.11.14.jar
amazon_kclpy/jars/aws-java-sdk-s3-1.11.14.jar
amazon_kclpy/jars/commons-codec-1.9.jar
amazon_kclpy/jars/commons-lang-2.6.jar
amazon_kclpy/jars/commons-logging-1.1.3.jar
amazon_kclpy/jars/guava-18.0.jar
amazon_kclpy/jars/httpclient-4.5.2.jar
amazon_kclpy/jars/httpcore-4.4.4.jar
amazon_kclpy/jars/jackson-annotations-2.6.0.jar
amazon_kclpy/jars/jackson-core-2.6.6.jar
amazon_kclpy/jars/jackson-databind-2.6.6.jar
amazon_kclpy/jars/jackson-dataformat-cbor-2.6.6.jar
amazon_kclpy/jars/joda-time-2.8.1.jar
amazon_kclpy/jars/protobuf-java-2.6.1.jar
amazon_kclpy_test.egg-info/PKG-INFO
amazon_kclpy_test.egg-info/SOURCES.txt
amazon_kclpy_test.egg-info/dependency_links.txt
amazon_kclpy_test.egg-info/not-zip-safe
amazon_kclpy_test.egg-info/requires.txt
amazon_kclpy_test.egg-info/top_level.txt
samples/__init__.py
samples/amazon_kclpy_helper.py
samples/sample.properties
samples/sample_kclpy_app.py
samples/sample_kinesis_wordputter.py
test/test_amazon_kclpy.py
test/test_amazon_kclpy_input_output_integration.py