Metadata-Version: 1.0
Name: amazon-kclpy-test
Version: 1.3.0
Summary: A python interface for the Amazon Kinesis Client Library MultiLangDaemon
Home-page: https://github.com/awslabs/amazon-kinesis-client-python
Author: UNKNOWN
Author-email: UNKNOWN
License: Amazon Software License
Keywords: amazon kinesis client library python
Platform: UNKNOWN
